upyflashed/__init__.py
upyflashed/microbit_path.py
upyflashed/reflash.py
upyflashed-0.1.2.dist-info/DESCRIPTION.rst
upyflashed-0.1.2.dist-info/METADATA
upyflashed-0.1.2.dist-info/RECORD
upyflashed-0.1.2.dist-info/WHEEL
upyflashed-0.1.2.dist-info/entry_points.txt
upyflashed-0.1.2.dist-info/metadata.json
upyflashed-0.1.2.dist-info/top_level.txt
