Metadata-Version: 2.0
Name: upyflashed
Version: 0.1.2
Summary: A command to watch for new hex files from upyed and flash the micro:bit immediately
Home-page: https://github.com/tomviner/upyflashed
Author: Tom Viner
Author-email: upyflashed@viner.tv
License: Apache
Platform: UNKNOWN
Requires-Dist: psutil
